kudra_cloud_client/__init__.py
kudra_cloud_client/kudra_cloud_client.py
KudraCloudClient-0.0.19.dist-info/LICENSE.txt
KudraCloudClient-0.0.19.dist-info/METADATA
KudraCloudClient-0.0.19.dist-info/WHEEL
KudraCloudClient-0.0.19.dist-info/top_level.txt
KudraCloudClient-0.0.19.dist-info/RECORD
