Metadata-Version: 2.1
Name: KudraCloudClient
Version: 0.0.19
Summary: A client for Kudra Cloud
Home-page: https://github.com/ubiai-incorporated/KudraCloudClient
Author: UBUAI Inc
Author-email: admin@ubiai.tools
License: UNKNOWN
Project-URL: Bug Tracker, https://github.com/ubiai-incorporated/KudraCloudClient
Platform: UNKNOWN
Classifier: Programming Language :: Python :: 3
Classifier: License :: OSI Approved :: MIT License
Classifier: Operating System :: OS Independent
Requires: tuspy
Requires: requests
Requires-Python: >=3.8
Requires-Dist: requests
Requires-Dist: tuspy
